{
    "home/metchadekiru": "めっちゃできる～！ガチでやりたい～！！\nって事があんの、やっぱ尊敬～ってなるよね。\nあたしも夢とか見つけてぇ～！！",
    "home/naninani_hima": "なになに？暇してんの～？\nじゃあ、あたしとどっか遊びに行こーよ。\n細かい事は、ノリで決めてく感じで！",
    "home/isekainoyumi": "異世界の弓、むっっっっっず！！！！\nこれ、ちょっとアーチェリーやってた程度の\nあたしじゃ絶対に無理だわ。\nちぇー。魔法の弓とか欲しかったんだけどなー。",
    "home/maa_atashimo": "まー、あたしもこう見えて元お嬢様なんで？\nお茶もピアノも、ひと通りはできましてよ？\nガチな人には敵いませんけど。うふふ。",
    "home/ehhehhe_atashino": "えっへっへ～。\nあたしの名前、古風でめっちゃよきでしょ～？\n昔はコンプ、ヤバかったんだけどね。\n今はまーじ気に入ってるんだ～！",
    "home/chochocho_kiite": "ちょちょちょっ、聞いて～！\nあたし、よく組む同中の子がいんだけどさ。\nその子が、ありえんくらい格好よすぎんの～！！\nは～～～……惚れるぜ～～～……。",
    "ally/join": "うぇーい★一年の朝戸ヤヱでーす！\n最近は冒険者やったり、異世界観光したり\nなんかいい感じで自由にやってまーす。\nよろしくお願いしますねー、先輩★",
    "ally/evolution": "やっぱり、また自由な渋谷にしたいしさ。 \n大好きなものも見つけたいし。 \nこれからも一緒に頑張ろーね！ \nもちろん、アゲてく感じでよろ！"
}