{
    "sequences": [
        {
            "begin": 1,
            "end": 8,
            "name": "start",
            "kind": "pass"
        },
        {
            "begin": 9,
            "end": 42,
            "name": "loop",
            "kind": "loop"
        },
        {
            "begin": 43,
            "end": 59,
            "name": "end",
            "kind": "once"
        }
    ],
    "sounds": [
        {
            "path": "sound_effect/wind/se_screw_thrust_big",
            "begin": 2,
            "loop": 1,
            "end": -1,
            "volume": -1
        }
    ],
    "points": [],
    "circles": [],
    "rectangles": [],
    "matrices": []
}