{
    "sequences": [
        {
            "begin": 1,
            "end": 263,
            "name": "scene0",
            "kind": "pass"
        },
        {
            "begin": 264,
            "end": 265,
            "name": "end0",
            "kind": "once"
        },
        {
            "begin": 266,
            "end": 363,
            "name": "scene1",
            "kind": "pass"
        },
        {
            "begin": 364,
            "end": 365,
            "name": "end1",
            "kind": "once"
        },
        {
            "begin": 366,
            "end": 453,
            "name": "scene2",
            "kind": "pass"
        },
        {
            "begin": 454,
            "end": 455,
            "name": "end2",
            "kind": "once"
        },
        {
            "begin": 456,
            "end": 473,
            "name": "scene3",
            "kind": "pass"
        },
        {
            "begin": 474,
            "end": 475,
            "name": "end3",
            "kind": "once"
        },
        {
            "begin": 476,
            "end": 513,
            "name": "scene4",
            "kind": "pass"
        },
        {
            "begin": 514,
            "end": 515,
            "name": "end4",
            "kind": "once"
        },
        {
            "begin": 516,
            "end": 668,
            "name": "scene5",
            "kind": "pass"
        },
        {
            "begin": 669,
            "end": 670,
            "name": "end5",
            "kind": "once"
        },
        {
            "begin": 671,
            "end": 703,
            "name": "scene6",
            "kind": "pass"
        },
        {
            "begin": 704,
            "end": 705,
            "name": "end6",
            "kind": "once"
        },
        {
            "begin": 706,
            "end": 773,
            "name": "scene7",
            "kind": "pass"
        },
        {
            "begin": 774,
            "end": 775,
            "name": "end7",
            "kind": "once"
        },
        {
            "begin": 776,
            "end": 893,
            "name": "scene8",
            "kind": "pass"
        },
        {
            "begin": 894,
            "end": 895,
            "name": "end8",
            "kind": "once"
        },
        {
            "begin": 896,
            "end": 913,
            "name": "scene9",
            "kind": "pass"
        },
        {
            "begin": 914,
            "end": 915,
            "name": "end9",
            "kind": "once"
        },
        {
            "begin": 916,
            "end": 933,
            "name": "scene10",
            "kind": "pass"
        },
        {
            "begin": 934,
            "end": 935,
            "name": "end10",
            "kind": "once"
        },
        {
            "begin": 936,
            "end": 958,
            "name": "scene11",
            "kind": "pass"
        },
        {
            "begin": 959,
            "end": 960,
            "name": "end11",
            "kind": "once"
        },
        {
            "begin": 961,
            "end": 1038,
            "name": "scene12",
            "kind": "pass"
        },
        {
            "begin": 1039,
            "end": 1040,
            "name": "end12",
            "kind": "once"
        },
        {
            "begin": 1041,
            "end": 1168,
            "name": "scene13",
            "kind": "pass"
        },
        {
            "begin": 1169,
            "end": 1170,
            "name": "end13",
            "kind": "once"
        },
        {
            "begin": 1171,
            "end": 1193,
            "name": "scene14",
            "kind": "pass"
        },
        {
            "begin": 1194,
            "end": 1195,
            "name": "end14",
            "kind": "once"
        },
        {
            "begin": 1196,
            "end": 1218,
            "name": "scene15",
            "kind": "pass"
        },
        {
            "begin": 1219,
            "end": 1220,
            "name": "end15",
            "kind": "once"
        },
        {
            "begin": 1221,
            "end": 1313,
            "name": "scene16",
            "kind": "pass"
        },
        {
            "begin": 1314,
            "end": 1315,
            "name": "end16",
            "kind": "once"
        },
        {
            "begin": 1316,
            "end": 1388,
            "name": "scene17",
            "kind": "pass"
        },
        {
            "begin": 1389,
            "end": 1390,
            "name": "end17",
            "kind": "once"
        },
        {
            "begin": 1391,
            "end": 1413,
            "name": "scene18",
            "kind": "pass"
        },
        {
            "begin": 1414,
            "end": 1415,
            "name": "end18",
            "kind": "once"
        },
        {
            "begin": 1416,
            "end": 1443,
            "name": "scene19",
            "kind": "pass"
        },
        {
            "begin": 1444,
            "end": 1445,
            "name": "end19",
            "kind": "once"
        },
        {
            "begin": 1446,
            "end": 1473,
            "name": "scene20",
            "kind": "pass"
        },
        {
            "begin": 1474,
            "end": 1475,
            "name": "end20",
            "kind": "once"
        },
        {
            "begin": 1476,
            "end": 1503,
            "name": "scene21",
            "kind": "pass"
        },
        {
            "begin": 1504,
            "end": 1505,
            "name": "end21",
            "kind": "once"
        },
        {
            "begin": 1506,
            "end": 1583,
            "name": "scene22",
            "kind": "pass"
        },
        {
            "begin": 1584,
            "end": 1585,
            "name": "end22",
            "kind": "once"
        },
        {
            "begin": 1586,
            "end": 1613,
            "name": "scene23",
            "kind": "pass"
        },
        {
            "begin": 1614,
            "end": 1615,
            "name": "end23",
            "kind": "once"
        },
        {
            "begin": 1616,
            "end": 1693,
            "name": "scene24",
            "kind": "pass"
        },
        {
            "begin": 1694,
            "end": 1695,
            "name": "end24",
            "kind": "once"
        },
        {
            "begin": 1696,
            "end": 1843,
            "name": "scene25",
            "kind": "pass"
        },
        {
            "begin": 1844,
            "end": 1845,
            "name": "end25",
            "kind": "once"
        },
        {
            "begin": 1846,
            "end": 2003,
            "name": "scene26",
            "kind": "pass"
        },
        {
            "begin": 2004,
            "end": 2005,
            "name": "end26",
            "kind": "once"
        },
        {
            "begin": 2006,
            "end": 2033,
            "name": "scene27",
            "kind": "pass"
        },
        {
            "begin": 2034,
            "end": 2035,
            "name": "end27",
            "kind": "once"
        },
        {
            "begin": 2036,
            "end": 2063,
            "name": "scene27a",
            "kind": "pass"
        },
        {
            "begin": 2064,
            "end": 2065,
            "name": "end27a",
            "kind": "once"
        },
        {
            "begin": 2066,
            "end": 2138,
            "name": "scene28",
            "kind": "pass"
        },
        {
            "begin": 2139,
            "end": 2140,
            "name": "end28",
            "kind": "once"
        },
        {
            "begin": 2141,
            "end": 2208,
            "name": "scene29",
            "kind": "pass"
        },
        {
            "begin": 2209,
            "end": 2210,
            "name": "end29",
            "kind": "once"
        },
        {
            "begin": 2211,
            "end": 2453,
            "name": "scene30",
            "kind": "pass"
        },
        {
            "begin": 2454,
            "end": 2455,
            "name": "end30",
            "kind": "once"
        },
        {
            "begin": 2456,
            "end": 2482,
            "name": "scene31",
            "kind": "pass"
        },
        {
            "begin": 2483,
            "end": 2484,
            "name": "end31",
            "kind": "once"
        },
        {
            "begin": 2485,
            "end": 2593,
            "name": "scene32",
            "kind": "pass"
        },
        {
            "begin": 2594,
            "end": 2595,
            "name": "end32",
            "kind": "once"
        },
        {
            "begin": 2596,
            "end": 2668,
            "name": "scene33",
            "kind": "pass"
        },
        {
            "begin": 2669,
            "end": 2670,
            "name": "end33",
            "kind": "once"
        },
        {
            "begin": 2671,
            "end": 2743,
            "name": "scene34",
            "kind": "pass"
        },
        {
            "begin": 2744,
            "end": 2745,
            "name": "end34",
            "kind": "once"
        },
        {
            "begin": 2746,
            "end": 2783,
            "name": "scene35",
            "kind": "pass"
        },
        {
            "begin": 2784,
            "end": 2785,
            "name": "end35",
            "kind": "once"
        },
        {
            "begin": 2786,
            "end": 2803,
            "name": "scene36",
            "kind": "pass"
        },
        {
            "begin": 2804,
            "end": 2805,
            "name": "end36",
            "kind": "once"
        },
        {
            "begin": 2806,
            "end": 2883,
            "name": "scene37",
            "kind": "pass"
        },
        {
            "begin": 2884,
            "end": 2885,
            "name": "end37",
            "kind": "once"
        },
        {
            "begin": 2886,
            "end": 2958,
            "name": "scene38",
            "kind": "pass"
        },
        {
            "begin": 2959,
            "end": 2960,
            "name": "end38",
            "kind": "once"
        },
        {
            "begin": 2961,
            "end": 3073,
            "name": "scene39",
            "kind": "pass"
        },
        {
            "begin": 3074,
            "end": 3075,
            "name": "end39",
            "kind": "once"
        },
        {
            "begin": 3076,
            "end": 3209,
            "name": "scene40",
            "kind": "pass"
        },
        {
            "begin": 3210,
            "end": 3210,
            "name": "end40",
            "kind": "stop"
        }
    ],
    "sounds": [
        {
            "path": "sound_effect/situation/se_question",
            "begin": 170,
            "loop": 1,
            "end": -1,
            "volume": -1
        },
        {
            "path": "sound_effect/situation/se_jump_up",
            "begin": 242,
            "loop": 1,
            "end": -1,
            "volume": -1
        },
        {
            "path": "sound_effect/situation/se_funny_bump",
            "begin": 270,
            "loop": 1,
            "end": -1,
            "volume": -1
        },
        {
            "path": "sound_effect/battle_common/se_enemy_damage_normal",
            "begin": 310,
            "loop": 1,
            "end": -1,
            "volume": -1
        },
        {
            "path": "sound_effect/battle_common/se_player_guard",
            "begin": 340,
            "loop": 1,
            "end": -1,
            "volume": -1
        },
        {
            "path": "sound_effect/situation/se_push",
            "begin": 480,
            "loop": 1,
            "end": -1,
            "volume": -1
        },
        {
            "path": "sound_effect/situation/se_emote_sweat",
            "begin": 600,
            "loop": 1,
            "end": -1,
            "volume": -1
        },
        {
            "path": "sound_effect/battle_common/se_enemy_escape",
            "begin": 709,
            "loop": 1,
            "end": -1,
            "volume": -1
        },
        {
            "path": "sound_effect/battle_common/se_short_dash03",
            "begin": 780,
            "loop": 1,
            "end": -1,
            "volume": -1
        },
        {
            "path": "sound_effect/battle_common/se_enemy_damage_critical",
            "begin": 789,
            "loop": 1,
            "end": -1,
            "volume": -1
        },
        {
            "path": "sound_effect/situation/se_emote_happning",
            "begin": 790,
            "loop": 1,
            "end": -1,
            "volume": -1
        },
        {
            "path": "sound_effect/battle_common/se_enemy_damage_normal",
            "begin": 829,
            "loop": 1,
            "end": -1,
            "volume": -1
        },
        {
            "path": "sound_effect/battle_common/se_player_guard",
            "begin": 859,
            "loop": 1,
            "end": -1,
            "volume": -1
        },
        {
            "path": "sound_effect/situation/se_emote_fun",
            "begin": 965,
            "loop": 1,
            "end": -1,
            "volume": -1
        },
        {
            "path": "sound_effect/situation/se_emote_angry",
            "begin": 1045,
            "loop": 1,
            "end": -1,
            "volume": -1
        },
        {
            "path": "sound_effect/situation/se_emote_notice_v03",
            "begin": 1320,
            "loop": 1,
            "end": -1,
            "volume": -1
        },
        {
            "path": "sound_effect/situation/se_emote_notice_v03",
            "begin": 1700,
            "loop": 1,
            "end": -1,
            "volume": -1
        },
        {
            "path": "sound_effect/situation/se_question",
            "begin": 1850,
            "loop": 1,
            "end": -1,
            "volume": -1
        },
        {
            "path": "sound_effect/situation/se_emote_shy",
            "begin": 2070,
            "loop": 1,
            "end": -1,
            "volume": -1
        },
        {
            "path": "sound_effect/situation/se_push",
            "begin": 2406,
            "loop": 1,
            "end": -1,
            "volume": -1
        },
        {
            "path": "sound_effect/situation/se_emote_fun",
            "begin": 2525,
            "loop": 1,
            "end": -1,
            "volume": -1
        },
        {
            "path": "sound_effect/situation/se_emote_notice_v03",
            "begin": 2600,
            "loop": 1,
            "end": -1,
            "volume": -1
        },
        {
            "path": "sound_effect/situation/se_emote_sweat",
            "begin": 2675,
            "loop": 1,
            "end": -1,
            "volume": -1
        },
        {
            "path": "sound_effect/situation/se_question",
            "begin": 2890,
            "loop": 1,
            "end": -1,
            "volume": -1
        }
    ],
    "points": [],
    "circles": [],
    "rectangles": [],
    "matrices": []
}