[
    {
        "n": "battle/effect/skill_unique/prince_zero/.gen/prince_zero/a",
        "w": 4,
        "h": 4,
        "x": 156,
        "y": 116
    },
    {
        "n": "battle/effect/skill_unique/prince_zero/.gen/prince_zero/aa",
        "w": 80,
        "h": 24,
        "x": 50,
        "y": 1,
        "r": true
    },
    {
        "n": "battle/effect/skill_unique/prince_zero/.gen/prince_zero/ab",
        "w": 10,
        "h": 10,
        "x": 287,
        "y": 53
    },
    {
        "n": "battle/effect/skill_unique/prince_zero/.gen/prince_zero/b",
        "w": 29,
        "h": 29,
        "x": 156,
        "y": 73,
        "fx": -1,
        "fy": -1,
        "fw": 30,
        "fh": 30
    },
    {
        "n": "battle/effect/skill_unique/prince_zero/.gen/prince_zero/c",
        "w": 4,
        "h": 4,
        "x": 168,
        "y": 104
    },
    {
        "n": "battle/effect/skill_unique/prince_zero/.gen/prince_zero/d",
        "w": 30,
        "h": 48,
        "x": 1,
        "y": 70
    },
    {
        "n": "battle/effect/skill_unique/prince_zero/.gen/prince_zero/e",
        "w": 48,
        "h": 30,
        "x": 187,
        "y": 53,
        "r": true
    },
    {
        "n": "battle/effect/skill_unique/prince_zero/.gen/prince_zero/f",
        "w": 10,
        "h": 10,
        "x": 287,
        "y": 65
    },
    {
        "n": "battle/effect/skill_unique/prince_zero/.gen/prince_zero/g",
        "w": 39,
        "h": 39,
        "x": 83,
        "y": 83,
        "fx": -1,
        "fy": -1,
        "fw": 40,
        "fh": 40
    },
    {
        "n": "battle/effect/skill_unique/prince_zero/.gen/prince_zero/h",
        "w": 8,
        "h": 6,
        "x": 287,
        "y": 77,
        "r": true,
        "fx": -1,
        "fy": 0,
        "fw": 7,
        "fh": 8
    },
    {
        "n": "battle/effect/skill_unique/prince_zero/.gen/prince_zero/i",
        "w": 14,
        "h": 11,
        "x": 33,
        "y": 70,
        "r": true
    },
    {
        "n": "battle/effect/skill_unique/prince_zero/.gen/prince_zero/j",
        "w": 67,
        "h": 28,
        "x": 50,
        "y": 53,
        "r": true
    },
    {
        "n": "battle/effect/skill_unique/prince_zero/.gen/prince_zero/k",
        "w": 10,
        "h": 10,
        "x": 156,
        "y": 104
    },
    {
        "n": "battle/effect/skill_unique/prince_zero/.gen/prince_zero/l",
        "w": 4,
        "h": 4,
        "x": 162,
        "y": 116
    },
    {
        "n": "battle/effect/skill_unique/prince_zero/.gen/prince_zero/m",
        "w": 80,
        "h": 24,
        "x": 50,
        "y": 27,
        "r": true
    },
    {
        "n": "battle/effect/skill_unique/prince_zero/.gen/prince_zero/n",
        "w": 80,
        "h": 24,
        "x": 132,
        "y": 1,
        "r": true
    },
    {
        "n": "battle/effect/skill_unique/prince_zero/.gen/prince_zero/o",
        "w": 48,
        "h": 30,
        "x": 237,
        "y": 53,
        "r": true
    },
    {
        "n": "battle/effect/skill_unique/prince_zero/.gen/prince_zero/p",
        "w": 48,
        "h": 30,
        "x": 33,
        "y": 83,
        "r": true
    },
    {
        "n": "battle/effect/skill_unique/prince_zero/.gen/prince_zero/q",
        "w": 29,
        "h": 29,
        "x": 237,
        "y": 85,
        "fx": -1,
        "fy": -1,
        "fw": 30,
        "fh": 30
    },
    {
        "n": "battle/effect/skill_unique/prince_zero/.gen/prince_zero/r",
        "w": 47,
        "h": 67,
        "x": 1,
        "y": 1
    },
    {
        "n": "battle/effect/skill_unique/prince_zero/.gen/prince_zero/s",
        "w": 29,
        "h": 29,
        "x": 268,
        "y": 85,
        "fx": -1,
        "fy": -1,
        "fw": 30,
        "fh": 30
    },
    {
        "n": "battle/effect/skill_unique/prince_zero/.gen/prince_zero/t",
        "w": 80,
        "h": 24,
        "x": 132,
        "y": 27,
        "r": true
    },
    {
        "n": "battle/effect/skill_unique/prince_zero/.gen/prince_zero/u",
        "w": 80,
        "h": 24,
        "x": 214,
        "y": 1,
        "r": true
    },
    {
        "n": "battle/effect/skill_unique/prince_zero/.gen/prince_zero/v",
        "w": 66,
        "h": 18,
        "x": 119,
        "y": 53,
        "r": true,
        "fx": -6,
        "fy": -4,
        "fw": 24,
        "fh": 74
    },
    {
        "n": "battle/effect/skill_unique/prince_zero/.gen/prince_zero/w",
        "w": 4,
        "h": 4,
        "x": 168,
        "y": 110
    },
    {
        "n": "battle/effect/skill_unique/prince_zero/.gen/prince_zero/x",
        "w": 30,
        "h": 48,
        "x": 124,
        "y": 73
    },
    {
        "n": "battle/effect/skill_unique/prince_zero/.gen/prince_zero/y",
        "w": 48,
        "h": 30,
        "x": 187,
        "y": 85,
        "r": true
    },
    {
        "n": "battle/effect/skill_unique/prince_zero/.gen/prince_zero/z",
        "w": 80,
        "h": 24,
        "x": 214,
        "y": 27,
        "r": true
    }
]