[
    {
        "n": "gacha/feature_movie/new_character_pickup_38/sleep_puppy/.gen/feature/a",
        "w": 10,
        "h": 10,
        "x": 921,
        "y": 923
    },
    {
        "n": "gacha/feature_movie/new_character_pickup_38/sleep_puppy/.gen/feature/b",
        "w": 233,
        "h": 233,
        "x": 819,
        "y": 688
    },
    {
        "n": "gacha/feature_movie/new_character_pickup_38/sleep_puppy/.gen/feature/c",
        "w": 124,
        "h": 124,
        "x": 1289,
        "y": 741,
        "fx": -1,
        "fy": -1,
        "fw": 126,
        "fh": 126
    },
    {
        "n": "gacha/feature_movie/new_character_pickup_38/sleep_puppy/.gen/feature/d",
        "w": 233,
        "h": 48,
        "x": 1054,
        "y": 813,
        "fx": 0,
        "fy": -6,
        "fw": 233,
        "fh": 54
    },
    {
        "n": "gacha/feature_movie/new_character_pickup_38/sleep_puppy/.gen/feature/e",
        "w": 232,
        "h": 70,
        "x": 1054,
        "y": 741,
        "fx": -9,
        "fy": -2,
        "fw": 251,
        "fh": 75
    },
    {
        "n": "gacha/feature_movie/new_character_pickup_38/sleep_puppy/.gen/feature/f",
        "w": 371,
        "h": 51,
        "x": 1054,
        "y": 688,
        "fx": -1,
        "fy": -6,
        "fw": 372,
        "fh": 57
    },
    {
        "n": "gacha/feature_movie/new_character_pickup_38/sleep_puppy/.gen/feature/g",
        "w": 98,
        "h": 10,
        "x": 1054,
        "y": 863,
        "r": true,
        "fx": 0,
        "fy": -2,
        "fw": 10,
        "fh": 100
    },
    {
        "n": "gacha/feature_movie/new_character_pickup_38/sleep_puppy/.gen/feature/h",
        "w": 631,
        "h": 685,
        "x": 819,
        "y": 1,
        "fx": -183,
        "fy": -317,
        "fw": 1038,
        "fh": 1040
    },
    {
        "n": "gacha/feature_movie/new_character_pickup_38/sleep_puppy/.gen/feature/i",
        "w": 10,
        "h": 97,
        "x": 1415,
        "y": 741,
        "r": true,
        "fx": 0,
        "fy": 0,
        "fw": 100,
        "fh": 10
    },
    {
        "n": "gacha/feature_movie/new_character_pickup_38/sleep_puppy/.gen/feature/j",
        "w": 816,
        "h": 940,
        "x": 1,
        "y": 1,
        "fx": -403,
        "fy": -345,
        "fw": 1219,
        "fh": 1940
    },
    {
        "n": "gacha/feature_movie/new_character_pickup_38/sleep_puppy/.gen/feature/k",
        "w": 14,
        "h": 28,
        "x": 1427,
        "y": 688,
        "r": true
    },
    {
        "n": "gacha/feature_movie/new_character_pickup_38/sleep_puppy/.gen/feature/l",
        "w": 100,
        "h": 10,
        "x": 819,
        "y": 923,
        "r": true
    },
    {
        "n": "gacha/feature_movie/new_character_pickup_38/sleep_puppy/.gen/feature/m",
        "w": 10,
        "h": 10,
        "x": 1054,
        "y": 875
    },
    {
        "n": "gacha/feature_movie/new_character_pickup_38/sleep_puppy/.gen/feature/n",
        "w": 10,
        "h": 10,
        "x": 1154,
        "y": 863
    }
]