[
    {
        "n": "battle/effect/skill_unique/white_tiger_xm20/.gen/white_tiger_xm20_all/a",
        "w": 83,
        "h": 102,
        "x": 161,
        "y": 1
    },
    {
        "n": "battle/effect/skill_unique/white_tiger_xm20/.gen/white_tiger_xm20_all/b",
        "w": 83,
        "h": 102,
        "x": 192,
        "y": 105
    },
    {
        "n": "battle/effect/skill_unique/white_tiger_xm20/.gen/white_tiger_xm20_all/c",
        "w": 83,
        "h": 102,
        "x": 246,
        "y": 1
    },
    {
        "n": "battle/effect/skill_unique/white_tiger_xm20/.gen/white_tiger_xm20_all/d",
        "w": 57,
        "h": 90,
        "x": 331,
        "y": 1
    },
    {
        "n": "battle/effect/skill_unique/white_tiger_xm20/.gen/white_tiger_xm20_all/e",
        "w": 77,
        "h": 83,
        "x": 390,
        "y": 1,
        "r": true
    },
    {
        "n": "battle/effect/skill_unique/white_tiger_xm20/.gen/white_tiger_xm20_all/f",
        "w": 29,
        "h": 29,
        "x": 513,
        "y": 138,
        "fx": 0,
        "fy": -1,
        "fw": 30,
        "fh": 30
    },
    {
        "n": "battle/effect/skill_unique/white_tiger_xm20/.gen/white_tiger_xm20_all/g",
        "w": 60,
        "h": 60,
        "x": 465,
        "y": 171
    },
    {
        "n": "battle/effect/skill_unique/white_tiger_xm20/.gen/white_tiger_xm20_all/h",
        "w": 109,
        "h": 111,
        "x": 81,
        "y": 115,
        "r": true
    },
    {
        "n": "battle/effect/skill_unique/white_tiger_xm20/.gen/white_tiger_xm20_all/i",
        "w": 57,
        "h": 90,
        "x": 375,
        "y": 93
    },
    {
        "n": "battle/effect/skill_unique/white_tiger_xm20/.gen/white_tiger_xm20_all/j",
        "w": 77,
        "h": 83,
        "x": 434,
        "y": 86,
        "r": true
    },
    {
        "n": "battle/effect/skill_unique/white_tiger_xm20/.gen/white_tiger_xm20_all/k",
        "w": 77,
        "h": 83,
        "x": 469,
        "y": 1,
        "r": true
    },
    {
        "n": "battle/effect/skill_unique/white_tiger_xm20/.gen/white_tiger_xm20_all/l",
        "w": 4,
        "h": 4,
        "x": 1,
        "y": 235
    },
    {
        "n": "battle/effect/skill_unique/white_tiger_xm20/.gen/white_tiger_xm20_all/m",
        "w": 40,
        "h": 40,
        "x": 192,
        "y": 209
    },
    {
        "n": "battle/effect/skill_unique/white_tiger_xm20/.gen/white_tiger_xm20_all/n",
        "w": 40,
        "h": 40,
        "x": 234,
        "y": 209
    },
    {
        "n": "battle/effect/skill_unique/white_tiger_xm20/.gen/white_tiger_xm20_area/a",
        "w": 47,
        "h": 94,
        "x": 277,
        "y": 105,
        "r": true,
        "fx": -20,
        "fy": -1,
        "fw": 120,
        "fh": 120
    },
    {
        "n": "battle/effect/skill_unique/white_tiger_xm20/.gen/white_tiger_xm20_area/b",
        "w": 78,
        "h": 115,
        "x": 1,
        "y": 1,
        "fx": -41,
        "fy": -2,
        "fw": 120,
        "fh": 120
    },
    {
        "n": "battle/effect/skill_unique/white_tiger_xm20/.gen/white_tiger_xm20_area/c",
        "w": 47,
        "h": 94,
        "x": 326,
        "y": 105,
        "r": true,
        "fx": -20,
        "fy": -1,
        "fw": 120,
        "fh": 120
    },
    {
        "n": "battle/effect/skill_unique/white_tiger_xm20/.gen/white_tiger_xm20_area/d",
        "w": 78,
        "h": 115,
        "x": 1,
        "y": 118,
        "fx": -41,
        "fy": -2,
        "fw": 120,
        "fh": 120
    },
    {
        "n": "battle/effect/skill_unique/white_tiger_xm20/.gen/white_tiger_xm20_area/e",
        "w": 65,
        "h": 53,
        "x": 336,
        "y": 201,
        "r": true
    },
    {
        "n": "battle/effect/skill_unique/white_tiger_xm20/.gen/white_tiger_xm20_area/f",
        "w": 58,
        "h": 34,
        "x": 276,
        "y": 209,
        "r": true
    },
    {
        "n": "battle/effect/skill_unique/white_tiger_xm20/.gen/white_tiger_xm20_area/g",
        "w": 78,
        "h": 112,
        "x": 81,
        "y": 1,
        "fx": -38,
        "fy": -4,
        "fw": 120,
        "fh": 120
    },
    {
        "n": "battle/effect/skill_unique/white_tiger_xm20/.gen/white_tiger_xm20_area/h",
        "w": 50,
        "h": 50,
        "x": 513,
        "y": 86
    },
    {
        "n": "battle/effect/skill_unique/white_tiger_xm20/.gen/white_tiger_xm20_throw/a",
        "w": 60,
        "h": 63,
        "x": 403,
        "y": 185
    },
    {
        "n": "battle/effect/skill_unique/white_tiger_xm20/.gen/white_tiger_xm20_throw/b",
        "w": 83,
        "h": 102,
        "x": 192,
        "y": 105
    },
    {
        "n": "battle/effect/skill_unique/white_tiger_xm20/.gen/white_tiger_xm20_throw/c",
        "w": 83,
        "h": 102,
        "x": 161,
        "y": 1
    },
    {
        "n": "battle/effect/skill_unique/white_tiger_xm20/.gen/white_tiger_xm20_throw/d",
        "w": 83,
        "h": 102,
        "x": 246,
        "y": 1
    }
]