[
    {
        "n": "quest/event/animation_background/expert_single_event/hero_big_boss/.gen/background/a",
        "w": 98,
        "h": 272,
        "x": 377,
        "y": 348,
        "r": true,
        "fx": 0,
        "fy": 0,
        "fw": 272,
        "fh": 101
    },
    {
        "n": "quest/event/animation_background/expert_single_event/hero_big_boss/.gen/background/b",
        "w": 100,
        "h": 272,
        "x": 275,
        "y": 348,
        "r": true,
        "fx": 0,
        "fy": -442,
        "fw": 272,
        "fh": 542
    },
    {
        "n": "quest/event/animation_background/expert_single_event/hero_big_boss/.gen/background/c",
        "w": 106,
        "h": 81,
        "x": 275,
        "y": 263,
        "fx": -75,
        "fy": -63,
        "fw": 256,
        "fh": 256
    },
    {
        "n": "quest/event/animation_background/expert_single_event/hero_big_boss/.gen/background/d",
        "w": 17,
        "h": 43,
        "x": 1,
        "y": 545,
        "r": true
    },
    {
        "n": "quest/event/animation_background/expert_single_event/hero_big_boss/.gen/background/e",
        "w": 272,
        "h": 542,
        "x": 1,
        "y": 1
    },
    {
        "n": "quest/event/animation_background/expert_single_event/hero_big_boss/.gen/background/f",
        "w": 108,
        "h": 84,
        "x": 385,
        "y": 176,
        "fx": -74,
        "fy": -59,
        "fw": 256,
        "fh": 256
    },
    {
        "n": "quest/event/animation_background/expert_single_event/hero_big_boss/.gen/background/g",
        "w": 108,
        "h": 84,
        "x": 275,
        "y": 177,
        "fx": -74,
        "fy": -58,
        "fw": 256,
        "fh": 256
    },
    {
        "n": "quest/event/animation_background/expert_single_event/hero_big_boss/.gen/background/h",
        "w": 108,
        "h": 85,
        "x": 385,
        "y": 89,
        "fx": -74,
        "fy": -57,
        "fw": 256,
        "fh": 256
    },
    {
        "n": "quest/event/animation_background/expert_single_event/hero_big_boss/.gen/background/i",
        "w": 108,
        "h": 86,
        "x": 275,
        "y": 1,
        "fx": -74,
        "fy": -57,
        "fw": 256,
        "fh": 256
    },
    {
        "n": "quest/event/animation_background/expert_single_event/hero_big_boss/.gen/background/j",
        "w": 108,
        "h": 86,
        "x": 385,
        "y": 1,
        "fx": -74,
        "fy": -58,
        "fw": 256,
        "fh": 256
    },
    {
        "n": "quest/event/animation_background/expert_single_event/hero_big_boss/.gen/background/k",
        "w": 108,
        "h": 86,
        "x": 275,
        "y": 89,
        "fx": -74,
        "fy": -59,
        "fw": 256,
        "fh": 256
    },
    {
        "n": "quest/event/animation_background/expert_single_event/hero_big_boss/.gen/background/l",
        "w": 106,
        "h": 84,
        "x": 385,
        "y": 262,
        "fx": -75,
        "fy": -61,
        "fw": 256,
        "fh": 256
    }
]