[
    {
        "n": "character/psychic_projection_smr23/pixelart/special0006",
        "w": 23,
        "h": 11,
        "x": 233,
        "y": 232,
        "r": true,
        "fx": -123,
        "fy": -106,
        "fw": 256,
        "fh": 256
    },
    {
        "n": "character/psychic_projection_smr23/pixelart/special0012",
        "w": 23,
        "h": 11,
        "x": 233,
        "y": 244,
        "r": true,
        "fx": -123,
        "fy": -106,
        "fw": 256,
        "fh": 256
    },
    {
        "n": "character/psychic_projection_smr23/pixelart/special0018",
        "w": 11,
        "h": 24,
        "x": 245,
        "y": 294,
        "fx": -123,
        "fy": -105,
        "fw": 256,
        "fh": 256
    },
    {
        "n": "character/psychic_projection_smr23/pixelart/special0024",
        "w": 11,
        "h": 36,
        "x": 233,
        "y": 294,
        "fx": -123,
        "fy": -93,
        "fw": 256,
        "fh": 256
    },
    {
        "n": "character/psychic_projection_smr23/pixelart/special0030",
        "w": 15,
        "h": 37,
        "x": 241,
        "y": 156,
        "fx": -123,
        "fy": -92,
        "fw": 256,
        "fh": 256
    },
    {
        "n": "character/psychic_projection_smr23/pixelart/special0036",
        "w": 15,
        "h": 37,
        "x": 241,
        "y": 194,
        "fx": -123,
        "fy": -92,
        "fw": 256,
        "fh": 256
    },
    {
        "n": "character/psychic_projection_smr23/pixelart/special0042",
        "w": 16,
        "h": 37,
        "x": 233,
        "y": 256,
        "fx": -123,
        "fy": -92,
        "fw": 256,
        "fh": 256
    },
    {
        "n": "character/psychic_projection_smr23/pixelart/special0048",
        "w": 54,
        "h": 54,
        "x": 186,
        "y": 427,
        "fx": -103,
        "fy": -88,
        "fw": 256,
        "fh": 256
    },
    {
        "n": "character/psychic_projection_smr23/pixelart/special0054",
        "w": 65,
        "h": 64,
        "x": 0,
        "y": 364,
        "r": true,
        "fx": -97,
        "fy": -76,
        "fw": 256,
        "fh": 256
    },
    {
        "n": "character/psychic_projection_smr23/pixelart/special0060",
        "w": 78,
        "h": 65,
        "x": 0,
        "y": 226,
        "fx": -92,
        "fy": -68,
        "fw": 256,
        "fh": 256
    },
    {
        "n": "character/psychic_projection_smr23/pixelart/special0066",
        "w": 78,
        "h": 67,
        "x": 0,
        "y": 158,
        "fx": -92,
        "fy": -67,
        "fw": 256,
        "fh": 256
    },
    {
        "n": "character/psychic_projection_smr23/pixelart/special0072",
        "w": 76,
        "h": 71,
        "x": 0,
        "y": 292,
        "fx": -92,
        "fy": -63,
        "fw": 256,
        "fh": 256
    },
    {
        "n": "character/psychic_projection_smr23/pixelart/special0078",
        "w": 77,
        "h": 73,
        "x": 163,
        "y": 156,
        "r": true,
        "fx": -91,
        "fy": -61,
        "fw": 256,
        "fh": 256
    },
    {
        "n": "character/psychic_projection_smr23/pixelart/special0084",
        "w": 75,
        "h": 70,
        "x": 157,
        "y": 230,
        "r": true,
        "fx": -91,
        "fy": -64,
        "fw": 256,
        "fh": 256
    },
    {
        "n": "character/psychic_projection_smr23/pixelart/special0090",
        "w": 72,
        "h": 60,
        "x": 77,
        "y": 300,
        "r": true,
        "fx": -91,
        "fy": -67,
        "fw": 256,
        "fh": 256
    },
    {
        "n": "character/psychic_projection_smr23/pixelart/special0096",
        "w": 66,
        "h": 60,
        "x": 77,
        "y": 361,
        "r": true,
        "fx": -90,
        "fy": -69,
        "fw": 256,
        "fh": 256
    },
    {
        "n": "character/psychic_projection_smr23/pixelart/special0102",
        "w": 62,
        "h": 65,
        "x": 0,
        "y": 429,
        "r": true,
        "fx": -90,
        "fy": -74,
        "fw": 256,
        "fh": 256
    },
    {
        "n": "character/psychic_projection_smr23/pixelart/special0108",
        "w": 59,
        "h": 64,
        "x": 126,
        "y": 422,
        "r": true,
        "fx": -90,
        "fy": -78,
        "fw": 256,
        "fh": 256
    },
    {
        "n": "character/psychic_projection_smr23/pixelart/special0114",
        "w": 58,
        "h": 54,
        "x": 186,
        "y": 372,
        "fx": -95,
        "fy": -84,
        "fw": 256,
        "fh": 256
    },
    {
        "n": "character/psychic_projection_smr23/pixelart/special0120",
        "w": 71,
        "h": 70,
        "x": 150,
        "y": 301,
        "r": true,
        "fx": -95,
        "fy": -63,
        "fw": 256,
        "fh": 256
    },
    {
        "n": "character/psychic_projection_smr23/pixelart/special0126",
        "w": 86,
        "h": 78,
        "x": 0,
        "y": 0,
        "fx": -85,
        "fy": -59,
        "fw": 256,
        "fh": 256
    },
    {
        "n": "character/psychic_projection_smr23/pixelart/special0132",
        "w": 85,
        "h": 78,
        "x": 87,
        "y": 0,
        "fx": -86,
        "fy": -59,
        "fw": 256,
        "fh": 256
    },
    {
        "n": "character/psychic_projection_smr23/pixelart/special0138",
        "w": 83,
        "h": 79,
        "x": 173,
        "y": 0,
        "fx": -87,
        "fy": -58,
        "fw": 256,
        "fh": 256
    },
    {
        "n": "character/psychic_projection_smr23/pixelart/special0144",
        "w": 83,
        "h": 78,
        "x": 0,
        "y": 79,
        "fx": -87,
        "fy": -57,
        "fw": 256,
        "fh": 256
    },
    {
        "n": "character/psychic_projection_smr23/pixelart/special0150",
        "w": 80,
        "h": 75,
        "x": 167,
        "y": 80,
        "fx": -87,
        "fy": -59,
        "fw": 256,
        "fh": 256
    },
    {
        "n": "character/psychic_projection_smr23/pixelart/special0156",
        "w": 82,
        "h": 74,
        "x": 84,
        "y": 79,
        "fx": -87,
        "fy": -60,
        "fw": 256,
        "fh": 256
    },
    {
        "n": "character/psychic_projection_smr23/pixelart/special0162",
        "w": 78,
        "h": 73,
        "x": 84,
        "y": 154,
        "fx": -87,
        "fy": -61,
        "fw": 256,
        "fh": 256
    },
    {
        "n": "character/psychic_projection_smr23/pixelart/special0166",
        "w": 77,
        "h": 71,
        "x": 79,
        "y": 228,
        "fx": -87,
        "fy": -63,
        "fw": 256,
        "fh": 256
    },
    {
        "n": "character/psychic_projection_smr23/pixelart/special0168",
        "w": 62,
        "h": 64,
        "x": 63,
        "y": 429,
        "r": true,
        "fx": -99,
        "fy": -72,
        "fw": 256,
        "fh": 256
    },
    {
        "n": "character/psychic_projection_smr23/pixelart/special0192",
        "w": 32,
        "h": 31,
        "x": 222,
        "y": 331,
        "fx": -111,
        "fy": -103,
        "fw": 256,
        "fh": 256
    }
]