{
  "name": "New Faces Spotlight Portal",
  "banner": "dynamic/gacha_list_banner/new_character_pickup_13",
  "rarity3": [
    {
      "name": "Samantha",
      "rank": 3,
      "odd": 3786,
      "isPickup": true,
      "localRate": 5,
      "rate": 3.5
    },
    {
      "name": "Harlisha",
      "rank": 3,
      "odd": 1240,
      "isPickup": false,
      "localRate": 1.637,
      "rate": 1.146
    },
    {
      "name": "Cran",
      "rank": 3,
      "odd": 1240,
      "isPickup": false,
      "localRate": 1.637,
      "rate": 1.146
    },
    {
      "name": "Lilial",
      "rank": 3,
      "odd": 1240,
      "isPickup": false,
      "localRate": 1.637,
      "rate": 1.146
    },
    {
      "name": "Marnie",
      "rank": 3,
      "odd": 1240,
      "isPickup": false,
      "localRate": 1.637,
      "rate": 1.146
    },
    {
      "name": "Haaj",
      "rank": 3,
      "odd": 1240,
      "isPickup": false,
      "localRate": 1.637,
      "rate": 1.146
    },
    {
      "name": "Jin",
      "rank": 3,
      "odd": 1240,
      "isPickup": false,
      "localRate": 1.637,
      "rate": 1.146
    },
    {
      "name": "Trine",
      "rank": 3,
      "odd": 1240,
      "isPickup": false,
      "localRate": 1.637,
      "rate": 1.146
    },
    {
      "name": "Gilasrad",
      "rank": 3,
      "odd": 1240,
      "isPickup": false,
      "localRate": 1.637,
      "rate": 1.146
    },
    {
      "name": "Enni",
      "rank": 3,
      "odd": 1240,
      "isPickup": false,
      "localRate": 1.637,
      "rate": 1.146
    },
    {
      "name": "Jake",
      "rank": 3,
      "odd": 1240,
      "isPickup": false,
      "localRate": 1.637,
      "rate": 1.146
    },
    {
      "name": "Clara",
      "rank": 3,
      "odd": 1240,
      "isPickup": false,
      "localRate": 1.637,
      "rate": 1.146
    },
    {
      "name": "Keylos",
      "rank": 3,
      "odd": 1240,
      "isPickup": false,
      "localRate": 1.637,
      "rate": 1.146
    },
    {
      "name": "Trista",
      "rank": 3,
      "odd": 1240,
      "isPickup": false,
      "localRate": 1.637,
      "rate": 1.146
    },
    {
      "name": "Walter",
      "rank": 3,
      "odd": 1240,
      "isPickup": false,
      "localRate": 1.637,
      "rate": 1.146
    },
    {
      "name": "Elza",
      "rank": 3,
      "odd": 1240,
      "isPickup": false,
      "localRate": 1.637,
      "rate": 1.146
    },
    {
      "name": "Klaus",
      "rank": 3,
      "odd": 1240,
      "isPickup": false,
      "localRate": 1.637,
      "rate": 1.146
    },
    {
      "name": "Shirano",
      "rank": 3,
      "odd": 1240,
      "isPickup": false,
      "localRate": 1.637,
      "rate": 1.146
    },
    {
      "name": "Kaiyu",
      "rank": 3,
      "odd": 1240,
      "isPickup": false,
      "localRate": 1.637,
      "rate": 1.146
    },
    {
      "name": "Lassie",
      "rank": 3,
      "odd": 1240,
      "isPickup": false,
      "localRate": 1.637,
      "rate": 1.146
    },
    {
      "name": "Faf",
      "rank": 3,
      "odd": 1240,
      "isPickup": false,
      "localRate": 1.637,
      "rate": 1.146
    },
    {
      "name": "Rico",
      "rank": 3,
      "odd": 1240,
      "isPickup": false,
      "localRate": 1.637,
      "rate": 1.146
    },
    {
      "name": "Vargen",
      "rank": 3,
      "odd": 1240,
      "isPickup": false,
      "localRate": 1.637,
      "rate": 1.146
    },
    {
      "name": "Fiora",
      "rank": 3,
      "odd": 1240,
      "isPickup": false,
      "localRate": 1.637,
      "rate": 1.146
    },
    {
      "name": "Yuna",
      "rank": 3,
      "odd": 1240,
      "isPickup": false,
      "localRate": 1.637,
      "rate": 1.146
    },
    {
      "name": "Bonnie",
      "rank": 3,
      "odd": 1240,
      "isPickup": false,
      "localRate": 1.637,
      "rate": 1.146
    },
    {
      "name": "Taiga",
      "rank": 3,
      "odd": 1240,
      "isPickup": false,
      "localRate": 1.637,
      "rate": 1.146
    },
    {
      "name": "Claw",
      "rank": 3,
      "odd": 1240,
      "isPickup": false,
      "localRate": 1.637,
      "rate": 1.146
    },
    {
      "name": "Albert",
      "rank": 3,
      "odd": 1240,
      "isPickup": false,
      "localRate": 1.637,
      "rate": 1.146
    },
    {
      "name": "Kazuchi",
      "rank": 3,
      "odd": 1240,
      "isPickup": false,
      "localRate": 1.637,
      "rate": 1.146
    },
    {
      "name": "Tatiana",
      "rank": 3,
      "odd": 1240,
      "isPickup": false,
      "localRate": 1.637,
      "rate": 1.146
    },
    {
      "name": "Colt",
      "rank": 3,
      "odd": 1240,
      "isPickup": false,
      "localRate": 1.637,
      "rate": 1.146
    },
    {
      "name": "Sha Suzu",
      "rank": 3,
      "odd": 1240,
      "isPickup": false,
      "localRate": 1.637,
      "rate": 1.146
    },
    {
      "name": "Kate",
      "rank": 3,
      "odd": 1240,
      "isPickup": false,
      "localRate": 1.637,
      "rate": 1.146
    },
    {
      "name": "Evan",
      "rank": 3,
      "odd": 1240,
      "isPickup": false,
      "localRate": 1.637,
      "rate": 1.146
    },
    {
      "name": "Challua",
      "rank": 3,
      "odd": 1240,
      "isPickup": false,
      "localRate": 1.637,
      "rate": 1.146
    },
    {
      "name": "Naska",
      "rank": 3,
      "odd": 1240,
      "isPickup": false,
      "localRate": 1.637,
      "rate": 1.146
    },
    {
      "name": "Mew",
      "rank": 3,
      "odd": 1240,
      "isPickup": false,
      "localRate": 1.637,
      "rate": 1.146
    },
    {
      "name": "Folus",
      "rank": 3,
      "odd": 1240,
      "isPickup": false,
      "localRate": 1.637,
      "rate": 1.146
    },
    {
      "name": "Hartlief",
      "rank": 3,
      "odd": 1240,
      "isPickup": false,
      "localRate": 1.637,
      "rate": 1.146
    },
    {
      "name": "Conner",
      "rank": 3,
      "odd": 1240,
      "isPickup": false,
      "localRate": 1.637,
      "rate": 1.146
    },
    {
      "name": "Jester",
      "rank": 3,
      "odd": 1240,
      "isPickup": false,
      "localRate": 1.637,
      "rate": 1.146
    },
    {
      "name": "Kharo",
      "rank": 3,
      "odd": 1240,
      "isPickup": false,
      "localRate": 1.637,
      "rate": 1.146
    },
    {
      "name": "Corinna",
      "rank": 3,
      "odd": 1240,
      "isPickup": false,
      "localRate": 1.637,
      "rate": 1.146
    },
    {
      "name": "Marguerite",
      "rank": 3,
      "odd": 1240,
      "isPickup": false,
      "localRate": 1.637,
      "rate": 1.146
    },
    {
      "name": "Cecilia",
      "rank": 3,
      "odd": 1240,
      "isPickup": false,
      "localRate": 1.637,
      "rate": 1.146
    },
    {
      "name": "Aureo",
      "rank": 3,
      "odd": 1240,
      "isPickup": false,
      "localRate": 1.637,
      "rate": 1.146
    },
    {
      "name": "Raul",
      "rank": 3,
      "odd": 1240,
      "isPickup": false,
      "localRate": 1.637,
      "rate": 1.146
    },
    {
      "name": "Miles",
      "rank": 3,
      "odd": 1240,
      "isPickup": false,
      "localRate": 1.637,
      "rate": 1.146
    },
    {
      "name": "Luluca",
      "rank": 3,
      "odd": 1240,
      "isPickup": false,
      "localRate": 1.637,
      "rate": 1.146
    },
    {
      "name": "Meryll",
      "rank": 3,
      "odd": 1240,
      "isPickup": false,
      "localRate": 1.637,
      "rate": 1.146
    },
    {
      "name": "Nochel",
      "rank": 3,
      "odd": 1240,
      "isPickup": false,
      "localRate": 1.637,
      "rate": 1.146
    },
    {
      "name": "Falsche",
      "rank": 3,
      "odd": 1240,
      "isPickup": false,
      "localRate": 1.637,
      "rate": 1.146
    },
    {
      "name": "Jalil",
      "rank": 3,
      "odd": 1240,
      "isPickup": false,
      "localRate": 1.637,
      "rate": 1.146
    },
    {
      "name": "Arly",
      "rank": 3,
      "odd": 1240,
      "isPickup": false,
      "localRate": 1.637,
      "rate": 1.146
    },
    {
      "name": "Shion",
      "rank": 3,
      "odd": 1240,
      "isPickup": false,
      "localRate": 1.637,
      "rate": 1.146
    },
    {
      "name": "Adil",
      "rank": 3,
      "odd": 1240,
      "isPickup": false,
      "localRate": 1.637,
      "rate": 1.146
    },
    {
      "name": "Dorothea",
      "rank": 3,
      "odd": 1240,
      "isPickup": false,
      "localRate": 1.637,
      "rate": 1.146
    },
    {
      "name": "Rebecca",
      "rank": 3,
      "odd": 1240,
      "isPickup": false,
      "localRate": 1.637,
      "rate": 1.146
    }
  ],
  "rarity4": [
    {
      "name": "Luna",
      "rank": 4,
      "odd": 616,
      "isPickup": true,
      "localRate": 8,
      "rate": 2
    },
    {
      "name": "Hayz",
      "rank": 4,
      "odd": 616,
      "isPickup": true,
      "localRate": 8,
      "rate": 2
    },
    {
      "name": "Kyrie",
      "rank": 4,
      "odd": 147,
      "isPickup": false,
      "localRate": 1.909,
      "rate": 0.477
    },
    {
      "name": "Levy",
      "rank": 4,
      "odd": 147,
      "isPickup": false,
      "localRate": 1.909,
      "rate": 0.477
    },
    {
      "name": "Kannon",
      "rank": 4,
      "odd": 147,
      "isPickup": false,
      "localRate": 1.909,
      "rate": 0.477
    },
    {
      "name": "Azel",
      "rank": 4,
      "odd": 147,
      "isPickup": false,
      "localRate": 1.909,
      "rate": 0.477
    },
    {
      "name": "Bianca",
      "rank": 4,
      "odd": 147,
      "isPickup": false,
      "localRate": 1.909,
      "rate": 0.477
    },
    {
      "name": "Hanabi",
      "rank": 4,
      "odd": 147,
      "isPickup": false,
      "localRate": 1.909,
      "rate": 0.477
    },
    {
      "name": "Asukirimaru",
      "rank": 4,
      "odd": 147,
      "isPickup": false,
      "localRate": 1.909,
      "rate": 0.477
    },
    {
      "name": "Clyde",
      "rank": 4,
      "odd": 147,
      "isPickup": false,
      "localRate": 1.909,
      "rate": 0.477
    },
    {
      "name": "Mizuchi",
      "rank": 4,
      "odd": 147,
      "isPickup": false,
      "localRate": 1.909,
      "rate": 0.477
    },
    {
      "name": "Mordiaga",
      "rank": 4,
      "odd": 147,
      "isPickup": false,
      "localRate": 1.909,
      "rate": 0.477
    },
    {
      "name": "Yuwel",
      "rank": 4,
      "odd": 147,
      "isPickup": false,
      "localRate": 1.909,
      "rate": 0.477
    },
    {
      "name": "Sohvi",
      "rank": 4,
      "odd": 147,
      "isPickup": false,
      "localRate": 1.909,
      "rate": 0.477
    },
    {
      "name": "Saar",
      "rank": 4,
      "odd": 147,
      "isPickup": false,
      "localRate": 1.909,
      "rate": 0.477
    },
    {
      "name": "Liesel",
      "rank": 4,
      "odd": 147,
      "isPickup": false,
      "localRate": 1.909,
      "rate": 0.477
    },
    {
      "name": "Amelia",
      "rank": 4,
      "odd": 147,
      "isPickup": false,
      "localRate": 1.909,
      "rate": 0.477
    },
    {
      "name": "Alice",
      "rank": 4,
      "odd": 147,
      "isPickup": false,
      "localRate": 1.909,
      "rate": 0.477
    },
    {
      "name": "Sharon",
      "rank": 4,
      "odd": 147,
      "isPickup": false,
      "localRate": 1.909,
      "rate": 0.477
    },
    {
      "name": "Rudy",
      "rank": 4,
      "odd": 147,
      "isPickup": false,
      "localRate": 1.909,
      "rate": 0.477
    },
    {
      "name": "Adonis",
      "rank": 4,
      "odd": 147,
      "isPickup": false,
      "localRate": 1.909,
      "rate": 0.477
    },
    {
      "name": "Rams",
      "rank": 4,
      "odd": 147,
      "isPickup": false,
      "localRate": 1.909,
      "rate": 0.477
    },
    {
      "name": "Renoir",
      "rank": 4,
      "odd": 147,
      "isPickup": false,
      "localRate": 1.909,
      "rate": 0.477
    },
    {
      "name": "Regis",
      "rank": 4,
      "odd": 147,
      "isPickup": false,
      "localRate": 1.909,
      "rate": 0.477
    },
    {
      "name": "Eleanor",
      "rank": 4,
      "odd": 147,
      "isPickup": false,
      "localRate": 1.909,
      "rate": 0.477
    },
    {
      "name": "Mino",
      "rank": 4,
      "odd": 147,
      "isPickup": false,
      "localRate": 1.909,
      "rate": 0.477
    },
    {
      "name": "Kohane",
      "rank": 4,
      "odd": 147,
      "isPickup": false,
      "localRate": 1.909,
      "rate": 0.477
    },
    {
      "name": "Suzuka",
      "rank": 4,
      "odd": 147,
      "isPickup": false,
      "localRate": 1.909,
      "rate": 0.477
    },
    {
      "name": "Lou",
      "rank": 4,
      "odd": 147,
      "isPickup": false,
      "localRate": 1.909,
      "rate": 0.477
    },
    {
      "name": "Mia",
      "rank": 4,
      "odd": 147,
      "isPickup": false,
      "localRate": 1.909,
      "rate": 0.477
    },
    {
      "name": "Aurore",
      "rank": 4,
      "odd": 147,
      "isPickup": false,
      "localRate": 1.909,
      "rate": 0.477
    },
    {
      "name": "Soushiro",
      "rank": 4,
      "odd": 147,
      "isPickup": false,
      "localRate": 1.909,
      "rate": 0.477
    },
    {
      "name": "Melsele",
      "rank": 4,
      "odd": 147,
      "isPickup": false,
      "localRate": 1.909,
      "rate": 0.477
    },
    {
      "name": "Helga",
      "rank": 4,
      "odd": 147,
      "isPickup": false,
      "localRate": 1.909,
      "rate": 0.477
    },
    {
      "name": "Floretta",
      "rank": 4,
      "odd": 147,
      "isPickup": false,
      "localRate": 1.909,
      "rate": 0.477
    },
    {
      "name": "Lyla",
      "rank": 4,
      "odd": 147,
      "isPickup": false,
      "localRate": 1.909,
      "rate": 0.477
    },
    {
      "name": "Hopper",
      "rank": 4,
      "odd": 147,
      "isPickup": false,
      "localRate": 1.909,
      "rate": 0.477
    },
    {
      "name": "Illumine",
      "rank": 4,
      "odd": 147,
      "isPickup": false,
      "localRate": 1.909,
      "rate": 0.477
    },
    {
      "name": "Gerard",
      "rank": 4,
      "odd": 147,
      "isPickup": false,
      "localRate": 1.909,
      "rate": 0.477
    },
    {
      "name": "Ellya",
      "rank": 4,
      "odd": 147,
      "isPickup": false,
      "localRate": 1.909,
      "rate": 0.477
    },
    {
      "name": "Finn",
      "rank": 4,
      "odd": 147,
      "isPickup": false,
      "localRate": 1.909,
      "rate": 0.477
    },
    {
      "name": "Keira",
      "rank": 4,
      "odd": 147,
      "isPickup": false,
      "localRate": 1.909,
      "rate": 0.477
    },
    {
      "name": "Selgir",
      "rank": 4,
      "odd": 147,
      "isPickup": false,
      "localRate": 1.909,
      "rate": 0.477
    },
    {
      "name": "Marianne",
      "rank": 4,
      "odd": 147,
      "isPickup": false,
      "localRate": 1.909,
      "rate": 0.477
    },
    {
      "name": "Andy",
      "rank": 4,
      "odd": 147,
      "isPickup": false,
      "localRate": 1.909,
      "rate": 0.477
    },
    {
      "name": "Liam",
      "rank": 4,
      "odd": 147,
      "isPickup": false,
      "localRate": 1.909,
      "rate": 0.477
    }
  ],
  "rarity5": [
    {
      "name": "Nephtim",
      "rank": 5,
      "odd": 592,
      "isPickup": true,
      "localRate": 14.011,
      "rate": 0.7
    },
    {
      "name": "Olivia",
      "rank": 5,
      "odd": 592,
      "isPickup": true,
      "localRate": 14.011,
      "rate": 0.7
    },
    {
      "name": "Botan",
      "rank": 5,
      "odd": 592,
      "isPickup": true,
      "localRate": 14.011,
      "rate": 0.7
    },
    {
      "name": "Kikuno",
      "rank": 5,
      "odd": 79,
      "isPickup": false,
      "localRate": 1.869,
      "rate": 0.093
    },
    {
      "name": "Rolf",
      "rank": 5,
      "odd": 79,
      "isPickup": false,
      "localRate": 1.869,
      "rate": 0.093
    },
    {
      "name": "Vagner",
      "rank": 5,
      "odd": 79,
      "isPickup": false,
      "localRate": 1.869,
      "rate": 0.093
    },
    {
      "name": "Marina",
      "rank": 5,
      "odd": 79,
      "isPickup": false,
      "localRate": 1.869,
      "rate": 0.093
    },
    {
      "name": "Clarisse",
      "rank": 5,
      "odd": 79,
      "isPickup": false,
      "localRate": 1.869,
      "rate": 0.093
    },
    {
      "name": "Rakisha",
      "rank": 5,
      "odd": 79,
      "isPickup": false,
      "localRate": 1.869,
      "rate": 0.093
    },
    {
      "name": "Remnith",
      "rank": 5,
      "odd": 79,
      "isPickup": false,
      "localRate": 1.869,
      "rate": 0.093
    },
    {
      "name": "Selene",
      "rank": 5,
      "odd": 79,
      "isPickup": false,
      "localRate": 1.869,
      "rate": 0.093
    },
    {
      "name": "Cipher",
      "rank": 5,
      "odd": 79,
      "isPickup": false,
      "localRate": 1.869,
      "rate": 0.093
    },
    {
      "name": "Sonia",
      "rank": 5,
      "odd": 79,
      "isPickup": false,
      "localRate": 1.869,
      "rate": 0.093
    },
    {
      "name": "Suizen",
      "rank": 5,
      "odd": 79,
      "isPickup": false,
      "localRate": 1.869,
      "rate": 0.093
    },
    {
      "name": "Sera",
      "rank": 5,
      "odd": 79,
      "isPickup": false,
      "localRate": 1.869,
      "rate": 0.093
    },
    {
      "name": "Barrek",
      "rank": 5,
      "odd": 79,
      "isPickup": false,
      "localRate": 1.869,
      "rate": 0.093
    },
    {
      "name": "Metis",
      "rank": 5,
      "odd": 79,
      "isPickup": false,
      "localRate": 1.869,
      "rate": 0.093
    },
    {
      "name": "Inaho",
      "rank": 5,
      "odd": 79,
      "isPickup": false,
      "localRate": 1.869,
      "rate": 0.093
    },
    {
      "name": "Cagliostro",
      "rank": 5,
      "odd": 79,
      "isPickup": false,
      "localRate": 1.869,
      "rate": 0.093
    },
    {
      "name": "Miguel",
      "rank": 5,
      "odd": 79,
      "isPickup": false,
      "localRate": 1.869,
      "rate": 0.093
    },
    {
      "name": "Shywe",
      "rank": 5,
      "odd": 79,
      "isPickup": false,
      "localRate": 1.869,
      "rate": 0.093
    },
    {
      "name": "Phiria",
      "rank": 5,
      "odd": 79,
      "isPickup": false,
      "localRate": 1.869,
      "rate": 0.093
    },
    {
      "name": "Leon",
      "rank": 5,
      "odd": 79,
      "isPickup": false,
      "localRate": 1.869,
      "rate": 0.093
    },
    {
      "name": "Celtie",
      "rank": 5,
      "odd": 79,
      "isPickup": false,
      "localRate": 1.869,
      "rate": 0.093
    },
    {
      "name": "Libram",
      "rank": 5,
      "odd": 79,
      "isPickup": false,
      "localRate": 1.869,
      "rate": 0.093
    },
    {
      "name": "Bulleta",
      "rank": 5,
      "odd": 79,
      "isPickup": false,
      "localRate": 1.869,
      "rate": 0.093
    },
    {
      "name": "Teurgis",
      "rank": 5,
      "odd": 79,
      "isPickup": false,
      "localRate": 1.869,
      "rate": 0.093
    },
    {
      "name": "Nephtim",
      "rank": 5,
      "odd": 79,
      "isPickup": false,
      "localRate": 1.869,
      "rate": 0.093
    },
    {
      "name": "Razelt",
      "rank": 5,
      "odd": 79,
      "isPickup": false,
      "localRate": 1.869,
      "rate": 0.093
    },
    {
      "name": "Eclair",
      "rank": 5,
      "odd": 79,
      "isPickup": false,
      "localRate": 1.869,
      "rate": 0.093
    },
    {
      "name": "Carla",
      "rank": 5,
      "odd": 79,
      "isPickup": false,
      "localRate": 1.869,
      "rate": 0.093
    },
    {
      "name": "Mormia",
      "rank": 5,
      "odd": 79,
      "isPickup": false,
      "localRate": 1.869,
      "rate": 0.093
    },
    {
      "name": "Belsidia",
      "rank": 5,
      "odd": 79,
      "isPickup": false,
      "localRate": 1.869,
      "rate": 0.093
    },
    {
      "name": "Vyron",
      "rank": 5,
      "odd": 79,
      "isPickup": false,
      "localRate": 1.869,
      "rate": 0.093
    }
  ]
}